libname/101903321.py
libname/__init__.py
Topsis_Kritarth_101903321-0.0.1.dist-info/METADATA
Topsis_Kritarth_101903321-0.0.1.dist-info/WHEEL
Topsis_Kritarth_101903321-0.0.1.dist-info/top_level.txt
Topsis_Kritarth_101903321-0.0.1.dist-info/RECORD
